pyfitit/ML.py
pyfitit/__init__.py
pyfitit/adaptiveSampling.py
pyfitit/adf.py
pyfitit/ansys_indentation.py
pyfitit/curveFitting.py
pyfitit/descriptor.py
pyfitit/directMethod.py
pyfitit/exafs.py
pyfitit/executors.py
pyfitit/factor_analysis.py
pyfitit/fdmnes.py
pyfitit/fdmnesTest.py
pyfitit/feff.py
pyfitit/fileBrowser.py
pyfitit/funcModel.py
pyfitit/geometry.py
pyfitit/ihs.py
pyfitit/inverseMethod.py
pyfitit/mixture.py
pyfitit/molecule.py
pyfitit/mpi.py
pyfitit/msPathGroupManager.py
pyfitit/optimize.py
pyfitit/plotting.py
pyfitit/project.py
pyfitit/pyGDM.py
pyfitit/sampling.py
pyfitit/smoothLib.py
pyfitit/uiControls.py
pyfitit/utils.py
pyfitit/vasp_rdf_energy.py
pyfitit/w2auto.py
pyfitit/wbm.py
pyfitit/bin/Feff6ldist/LICENSE
pyfitit/bin/Feff6ldist/README
pyfitit/bin/Feff6ldist/chi.601
pyfitit/bin/Feff6ldist/chi.dat
pyfitit/bin/Feff6ldist/feff.inp
pyfitit/bin/Feff6ldist/feff0001.dat
pyfitit/bin/Feff6ldist/feff0002.dat
pyfitit/bin/Feff6ldist/feff0003.dat
pyfitit/bin/Feff6ldist/feff0004.dat
pyfitit/bin/Feff6ldist/feff0005.dat
pyfitit/bin/Feff6ldist/feff0006.dat
pyfitit/bin/Feff6ldist/feff0007.dat
pyfitit/bin/Feff6ldist/feff0008.dat
pyfitit/bin/Feff6ldist/feff0009.dat
pyfitit/bin/Feff6ldist/feff0010.dat
pyfitit/bin/Feff6ldist/feff0011.dat
pyfitit/bin/Feff6ldist/feff0012.dat
pyfitit/bin/Feff6ldist/feff0014.dat
pyfitit/bin/Feff6ldist/feff0015.dat
pyfitit/bin/Feff6ldist/feff6L.f
pyfitit/bin/Feff6ldist/feff6l
pyfitit/bin/Feff6ldist/feff6l.exe
pyfitit/bin/Feff6ldist/files.dat
pyfitit/bin/Feff6ldist/nstar.dat
pyfitit/bin/Feff6ldist/paths.dat
pyfitit/bin/Feff6ldist/phase.bin
pyfitit/bin/Feff6ldist/DOC/feff6L.doc
pyfitit/bin/fdmnes/fdmnes_linux64
pyfitit/bin/fdmnes/fdmnes_win64.exe
pyfitit/examples/Custom/Custom sampling.ipynb
pyfitit/examples/Custom/Custom sliders.ipynb
pyfitit/examples/EXAFS/00 Fitting EXAFS params.ipynb
pyfitit/examples/EXAFS/20 Calculate EXAFS for a set of geometries.ipynb
pyfitit/examples/EXAFS/50 Fitting EXAFS by sliders.ipynb
pyfitit-3.1.7.dist-info/LICENSE
pyfitit-3.1.7.dist-info/METADATA
pyfitit-3.1.7.dist-info/WHEEL
pyfitit-3.1.7.dist-info/top_level.txt
pyfitit-3.1.7.dist-info/RECORD
