Metadata-Version: 2.1
Name: pyfitit
Version: 3.1.7
Summary: Python implementation of FitIt software to fit spectra extended with additional features
Home-page: http://hpc.nano.sfedu.ru/pyfitit/
Author: Sergey Guda, Grigory Smolentsev, Alexander Soldatov, Carlo Lamberti, Alexander Guda, Oleg Usoltsev, Andrea Martini, Alexander Chebanny, Alexander Algasov, Danil Pashkov, Yuriy Fedorov
Author-email: gudasergey@gmail.com
Maintainer: Sergey Guda
Classifier: Programming Language :: Python :: 3
Classifier: License :: OSI Approved :: GNU General Public License v3 (GPLv3)
Classifier: Operating System :: OS Independent
License-File: LICENSE
Requires-Dist: ipywidgets (>=8.1.3)
Requires-Dist: jupyterlab (>=4.0.11)
Requires-Dist: jupyterlab-widgets (>=1.0.0)
Requires-Dist: ipympl (>=0.9.4)
Requires-Dist: jupytext (>=1.16.3)
Requires-Dist: tqdm (>=4.66.4)
Requires-Dist: scipy (>=1.13.1)
Requires-Dist: numba (>=0.59.1)
Requires-Dist: cycler (>=0.11.0)
Requires-Dist: statsmodels (>=0.14.2)
Requires-Dist: lmfit (>=1.3.1)
Requires-Dist: matplotlib (>=3.8.4)
Requires-Dist: numpy (>=1.26.4)
Requires-Dist: pandas (>=2.2.2)
Requires-Dist: parsy (>=2.1)
Requires-Dist: notebook (>=7.0.8)
Requires-Dist: nbformat (>=5.9.2)
Requires-Dist: toml (>=0.10.2)
Requires-Dist: pulp (>=2.9.0)
Requires-Dist: scikit-learn (>=1.4.2)
Requires-Dist: seaborn (>=0.13.2)
Requires-Dist: vasppy (>=0.7.1.0)
Requires-Dist: confsmooth (>=1.0.0)
Requires-Dist: openTSNE (>=1.0.1)
Requires-Dist: sqlalchemy (>=2.0.30)
Requires-Dist: ipynbname (>=2024.1.0.0)
Requires-Dist: widgetsnbextension (>=3.6.6)
Requires-Dist: xraydb (>=4.5.4)
Requires-Dist: openpyxl (>=3.1.2)
